guto/__init__.py
guto/const.py
guto/frame.py
guto/gui.py
guto/position.py
guto-0.0.1.21.dist-info/LICENSE
guto-0.0.1.21.dist-info/METADATA
guto-0.0.1.21.dist-info/WHEEL
guto-0.0.1.21.dist-info/top_level.txt
guto-0.0.1.21.dist-info/RECORD
