Metadata-Version: 2.1
Name: guto
Version: 0.0.1.21
Summary: easy gui-auto tools
Home-page: https://github.com/YifeiLiu-1997/guto
Author: YifeiLiu-1997
Author-email: lyfwork_mail@163.com
License: UNKNOWN
Platform: UNKNOWN
Classifier: Programming Language :: Python :: 3
Classifier: License :: OSI Approved :: MIT License
Classifier: Operating System :: OS Independent
License-File: LICENSE
Requires-Dist: pyautogui (>=0.9.53)
